setup.py
gaussian_binomial_dsnd/Binomialdistribution.py
gaussian_binomial_dsnd/Gaussiandistribution.py
gaussian_binomial_dsnd/Generaldistribution.py
gaussian_binomial_dsnd/__init__.py
gaussian_binomial_dsnd.egg-info/PKG-INFO
gaussian_binomial_dsnd.egg-info/SOURCES.txt
gaussian_binomial_dsnd.egg-info/dependency_links.txt
gaussian_binomial_dsnd.egg-info/not-zip-safe
gaussian_binomial_dsnd.egg-info/top_level.txt